{
  "type": "header",
  "name": "Header group",
  "sections": {
    "announcement-bar": {
      "type": "announcement-bar",
      "settings": {
        "show_announcement": true,
        "text": "🔥 Free shipping on orders over $75 — New drops every Friday!",
        "link": "/collections/all",
        "icon": "zap"
      }
    },
    "header": {
      "type": "header",
      "settings": {
        "menu": "main-menu",
        "logo_width": 160,
        "sticky": true
      }
    }
  },
  "order": ["announcement-bar", "header"]
}
